triangle.v
module triangle (clk, reset, nt, xi, yi, busy, po, xo, yo);
  input clk, reset, nt;
  input [2:0] xi, yi;
  output busy, po;
  output [2:0] xo, yo;
  
                   
parameter INIT = 2'b00;
parameter WRITE = 2'b01;
parameter COUNT = 2'b10;
parameter FINAL = 2'b11;

reg [1:0] st_curr;
reg [1:0] st_next;

reg [2:0] x1,x2,x3,y1,y2,y3;
reg [2:0]x_count,y_count;
reg [2:0] xo,yo;
//reg signed [2:0] dx,dy,dx1,dy1;
//reg nt, 
reg busy,po;
reg gg1;
wire signed [7:0]gg;

assign gg = ( ( y3 - y_count )*(x2 - x3) - (y3 - y2 )*(x_count - x3));

always @(*) begin
  if(gg>0)
    gg1=1;
  else if(gg<0)
    gg1=0;
  //else if(gg=0)
    //gg1=1;
end

/*always@(posedge clk or posedge reset)begin
if(reset)
	nt<=1;
else 
  nt<=0;
end*/

always@(posedge clk)begin
if(x1!=0 && x2==0)
  busy<=1;
else if(xo==x2 && yo==y3)
  busy<=0;
end

always@(posedge clk or posedge reset or negedge clk)begin
if(reset)
	st_curr <= INIT;
else 
	st_curr <= st_next;
end

always@(*)begin
case(st_curr)
  INIT :begin 
  //if(nt)
  if(x1 == 0)
    st_next = WRITE;
  else 
    st_next = INIT;
    end

  WRITE : begin
  if((x3!=0)   &&    (y3 != 0))
    st_next = COUNT;
  else
    st_next = WRITE;end

  COUNT : begin
  if((x_count == x3)   &&    (y_count == y3))
    st_next = FINAL;
  else
    st_next = COUNT;end

  FINAL : begin
      st_next = INIT;end
endcase
end


always@(*)begin
if(st_curr==INIT)begin
    x1=0;x2=0;x3=0;x_count=0;po<=0;
    y1=0;y2=0;y3=0;y_count=0;xo<=0;yo<=0;
end
end


always@(posedge clk)begin
if(st_curr == WRITE)begin
  if(x1==0 && nt==1)begin
    x1<=xi;
    y1<=yi;  end
  if(x1!=0 && x2==0)begin
    x2<=xi;
    y2<=yi;
    x_count<=x1;
    y_count<=y1;
    busy<=1;end
  if(x2!=0 && x3==0)begin
    x3<=xi;
    y3<=yi;
    end
end
end

always@(posedge clk)begin
if(st_curr == COUNT)begin
  if((x_count == x2) && (y_count != y3))begin
    x_count<=x1;
    y_count<=y_count+1;end
  else 

    x_count<=x_count+1;
end
end

always@(posedge clk)begin
if(st_curr == COUNT)begin
  if(gg1)begin
    xo<=x_count;
    yo<=y_count;
    po<=1; 
    end
  else if(x_count==x3 && y_count==y3)begin
    xo<=x_count;
    yo<=y_count;
    po<=1; 
  end
  else begin
    xo<=0;
    yo<=0;
    po<=0;
        //dx1<=x_count-x3;
    //dy1<=y_count-y3; end
end
end
end


always@(*)begin
if(st_curr == FINAL)begin
  if(x_count==x3 && y_count==y3)begin
    xo<=x_count;
    yo<=y_count;
    po<=1; 
  end
  else begin
    xo<=0;
    yo<=0;
    po<=0;
end
end
end


//((x_count-x3)*(dy))<=((y_count-y3)*(dx))




endmodule

testfixture.v
`timescale 100ps/10ps
`define CYCLE      100	// Modify your clock period here (unit: ns, resolution: 0.1ns)
`define INFILE1    "input.dat"
`define IN_LENGTH  6
`define INFILE2    "expect.dat"
`define OUT_LENGTH 28
`define SDF_FILE   "triangle.sdf"


module test;
parameter INPUT_DATA = `INFILE1;
parameter EXPECT_DATA = `INFILE2;
parameter period = `CYCLE * 10; 
reg     clk;
reg     reset;
reg     nt;
reg     [2:0] xi, yi;

wire    [2:0] xo, yo;
wire    po;
wire    busy;


integer i, j, k, l, out_f, err, pattern_num, total_num, total_cycle_num;
integer a, b, c, d;
reg [5:0]  data_base [0:`IN_LENGTH - 1];
reg [5:0]  data_base_expect [0:`OUT_LENGTH - 1];
reg [5:0]  data_tmp_expect;
reg [5:0]  data_tmp_i1, data_tmp_i2, data_tmp_i3;


triangle top(clk, reset, nt, xi, yi, busy, po, xo, yo);

//initial $sdf_annotate(`SDF_FILE,top);

initial	$readmemb(INPUT_DATA,  data_base);
initial	$readmemb(EXPECT_DATA,  data_base_expect);

initial begin
   $fsdbDumpfile("triangle.fsdb");
   $fsdbDumpvars;
   $fsdbDumpMDA();
   $dumpfile("tria.vcd");
   $dumpvars;
   
   clk   = 1'b1;
   reset = 1'b0;
   nt    = 1'b0;
   xi    = 3'bz;
   yi    = 3'bz;
   l = 0;
   i = 0;
   j = 0;
   k = 0;
   err = 0;
   pattern_num = 1 ; 
   total_num = 0 ;
end



initial begin
   out_f = $fopen("OUT.DAT");
   if (out_f == 0) begin
      $display("Output file open error !");
      $finish;
   end
end

always 
   #(period/2)  clk = ~clk;

initial begin 
   @(negedge clk)  
      reset = 1'b1;
      $display ("\n****** START to VERIFY the Triangel Rendering Enginen OPERATION ******\n");
      #(period - 0.1)
         reset = 1'b0;
   
   for(i = 0; i < `IN_LENGTH; i = i + k) begin
      if(busy == 1'b1) begin
         @(negedge clk)
            nt =1'b0;
            k  =0;
      end else begin
         k  = 3;
         // cycle 1
         @(negedge clk)
            nt = 1'b1;      
            #(`CYCLE*3)  // read x1 & y1
               data_tmp_i1 = data_base[i];
               xi = data_tmp_i1[5:3];
               yi = data_tmp_i1[2:0];
         @(posedge clk)
            #(`CYCLE*2)  // close x1 & y1 
               xi = 3'bz; 
               yi = 3'bz; 
         // cycle 2
         @(negedge clk)
            nt =1'b0;      
            #(`CYCLE*3)  // read x2 & y2
               data_tmp_i2 = data_base[i+1];
               xi = data_tmp_i2[5:3];
               yi = data_tmp_i2[2:0];
         @(posedge clk)
            #(`CYCLE*2)  // close x2 & y2 
               xi = 3'bz; 
               yi = 3'bz;
         // cycle 3
         @(negedge clk)
            #(`CYCLE*3)  // read x3 & y3
               data_tmp_i3 = data_base[i+2];
               xi = data_tmp_i3[5:3];
               yi = data_tmp_i3[2:0];
         @(posedge clk)
            #(`CYCLE*2)  // close x3 & y3 
               xi = 3'bz; 
               yi = 3'bz;
         
         $display("Waiting for the rendering operation of the triangle points with:"); 
         $display("(x1, y1)=(%h, %h)",data_tmp_i1[5:3], data_tmp_i1[2:0]); 
         $display("(x2, y2)=(%h, %h)",data_tmp_i2[5:3], data_tmp_i2[2:0]); 
         $display("(x3, y3)=(%h, %h)",data_tmp_i3[5:3], data_tmp_i3[2:0]); 
      end
   end
end 

always @(posedge clk) begin
   if (po ==1'b1) begin 
      data_tmp_expect = data_base_expect[l]; 
      if ((xo !== data_tmp_expect[5:3])|| (yo!== data_tmp_expect[2:0])) begin
         $display("ERROR at %d:xo=(%h) yo=(%h)!=expect xo=(%h), yo=(%h)",l 
         ,xo, yo, data_tmp_expect[5:3], data_tmp_expect[2:0]);
         err = err + 1 ;   
      end
      $fdisplay(out_f,"%h%h",xo,yo); 
      l = l + 1;
   end
    
   if( l == `OUT_LENGTH ) begin
      if (err == 0)
         $display("PASS! All data have been generated successfully!");
      else begin
         $display("---------------------------------------------");
         $display("There are %d errors!", err);
         $display("---------------------------------------------");
      end
      $display("---------------------------------------------");
      total_num = total_cycle_num * period; 
      $display("Total delay: %d ns", total_num );
      $display("---------------------------------------------");
      $finish;
   end
end

always @(posedge clk) begin
   if (reset == 1'b1) 
      total_cycle_num = 0 ;
   else 
      total_cycle_num = total_cycle_num + 1 ;
end 

endmodule

tria.vcd
$date
    Sep  5, 2022  00:08:40
$end
$version
    TOOL:	ncsim(64)	15.20-s039
$end
$timescale
    10 ps
$end

$scope module test $end
$var parameter 72 !    INPUT_DATA  $end
$var parameter 80 "    EXPECT_DATA  $end
$var parameter 32 #    period  $end
$var reg       1 $    clk  $end
$var reg       1 %    reset  $end
$var reg       1 &    nt  $end
$var reg       3 '    xi [2:0] $end
$var reg       3 (    yi [2:0] $end
$var wire      3 )    xo [2:0] $end
$var wire      3 *    yo [2:0] $end
$var wire      1 +    po  $end
$var wire      1 ,    busy  $end
$var integer  32 -    i  $end
$var integer  32 .    j  $end
$var integer  32 /    k  $end
$var integer  32 0    l  $end
$var integer  32 1    out_f  $end
$var integer  32 2    err  $end
$var integer  32 3    pattern_num  $end
$var integer  32 4    total_num  $end
$var integer  32 5    total_cycle_num  $end
$var integer  32 6    a  $end
$var integer  32 7    b  $end
$var integer  32 8    c  $end
$var integer  32 9    d  $end
$var reg       6 :    data_tmp_expect [5:0] $end
$var reg       6 ;    data_tmp_i1 [5:0] $end
$var reg       6 <    data_tmp_i2 [5:0] $end
$var reg       6 =    data_tmp_i3 [5:0] $end

$scope module top $end
$var wire      1 >    clk  $end
$var wire      1 ?    reset  $end
$var wire      1 @    nt  $end
$var wire      3 A    xi [2:0] $end
$var wire      3 B    yi [2:0] $end
$var reg       1 C    busy  $end
$var reg       1 D    po  $end
$var reg       3 E    xo [2:0] $end
$var reg       3 F    yo [2:0] $end
$var parameter  2 G    INIT  $end
$var parameter  2 H    WRITE  $end
$var parameter  2 I    COUNT  $end
$var parameter  2 J    FINAL  $end
$var reg       2 K    st_curr [1:0] $end
$var reg       2 L    st_next [1:0] $end
$var reg       3 M    x1 [2:0] $end
$var reg       3 N    x2 [2:0] $end
$var reg       3 O    x3 [2:0] $end
$var reg       3 P    y1 [2:0] $end
$var reg       3 Q    y2 [2:0] $end
$var reg       3 R    y3 [2:0] $end
$var reg       3 S    x_count [2:0] $end
$var reg       3 T    y_count [2:0] $end
$var reg       1 U    gg1  $end
$var wire      8 V    gg [7:0] $end
$upscope $end

$upscope $end

$enddefinitions $end
$dumpvars
b11 J
b10 I
b1 H
b0 G
b1111101000 #
b1100101011110000111000001100101011000110111010000101110011001000110000101110100 "
b11010010110111001110000011101010111010000101110011001000110000101110100 !
1$
0%
0&
bz '
bz (
bx )
bx *
x+
x,
b0 -
b0 .
b0 /
b0 0
b10 1
b0 2
b1 3
b0 4
bx 5
bx 6
bx 7
bx 8
bx 9
bx :
bx ;
bx <
bx =
1>
0?
0@
bz A
bz B
xC
xD
bx E
bx F
bx K
bx L
bx M
bx N
bx O
bx P
bx Q
bx R
bx S
bx T
xU
bx V
$end
#5000
0$
1%
1?
0>
b0 K
b0 L
b0 M
b0 N
b0 O
b0 S
b0 P
b0 Q
b0 R
b0 T
b1 L
b0 V
0D
b0 E
b0 F
b0 *
b0 )
0+
#10000
1$
b0 5
1>
0C
0,
#14999
0%
b11 /
0?
#15000
0$
1&
1@
0>
b1 K
#18000
b1001 ;
b1 '
b1 (
b1 B
b1 A
#20000
1$
b1 5
1>
b1 M
b1 P
#22000
bz '
bz (
bz B
bz A
#25000
0$
0&
0@
0>
#28000
b100001 <
b100 '
b1 (
b1 B
b100 A
#30000
1$
b10 5
1>
b100 N
b1 Q
b1 S
b1 T
1C
b11111101 V
1,
0U
#32000
bz '
bz (
bz B
bz A
#35000
0$
0>
#38000
b1111 =
b1 '
b111 (
b111 B
b1 A
#40000
1$
b11 5
1>
b1 O
b111 R
b10 L
b10010 V
1U
#42000
bz '
bz (
b11 -
bz B
bz A
#45000
0$
b0 /
0>
b10 K
#50000
1$
b100 5
1>
b10 S
b1 E
b1 F
1D
b1100 V
1+
b1 *
b1 )
#55000
0$
0>
#60000
1$
b1001 :
b1 0
b101 5
1>
b11 S
b10 E
b110 V
b10 )
#65000
0$
0>
#70000
1$
b10001 :
b10 0
b110 5
1>
b100 S
b11 E
b0 V
b11 )
#75000
0$
0>
#80000
1$
b11001 :
b11 0
b111 5
1>
b1 S
b10 T
b100 E
b1111 V
b100 )
#85000
0$
0>
#90000
1$
b100001 :
b100 0
b1000 5
1>
b10 S
b1 E
b10 F
b1001 V
b10 *
b1 )
#95000
0$
0>
#100000
1$
b1010 :
b101 0
b1001 5
1>
b11 S
b10 E
b11 V
b10 )
#105000
0$
0>
#110000
1$
b10010 :
b110 0
b1010 5
1>
b100 S
b11 E
b11111101 V
b11 )
0U
#115000
0$
0>
#120000
1$
b11010 :
b111 0
b1011 5
1>
b1 S
b11 T
b0 E
b0 F
0D
b1100 V
0+
b0 *
b0 )
1U
#125000
0$
0>
#130000
1$
b1100 5
1>
b10 S
b1 E
b11 F
1D
b110 V
1+
b11 *
b1 )
#135000
0$
0>
#140000
1$
b1011 :
b1000 0
b1101 5
1>
b11 S
b10 E
b0 V
b10 )
#145000
0$
0>
#150000
1$
b10011 :
b1001 0
b1110 5
1>
b100 S
b11 E
b11111010 V
b11 )
0U
#155000
0$
0>
#160000
1$
b11011 :
b1010 0
b1111 5
1>
b1 S
b100 T
b0 E
b0 F
0D
b1001 V
0+
b0 *
b0 )
1U
#165000
0$
0>
#170000
1$
b10000 5
1>
b10 S
b1 E
b100 F
1D
b11 V
1+
b100 *
b1 )
#175000
0$
0>
#180000
1$
b1100 :
b1011 0
b10001 5
1>
b11 S
b10 E
b11111101 V
b10 )
0U
#185000
0$
0>
#190000
1$
b10100 :
b1100 0
b10010 5
1>
b100 S
b0 E
b0 F
0D
b11110111 V
0+
b0 *
b0 )
#195000
0$
0>
#200000
1$
b10011 5
1>
b1 S
b101 T
b110 V
1U
#205000
0$
0>
#210000
1$
b10100 5
1>
b10 S
b1 E
b101 F
1D
b0 V
1+
b101 *
b1 )
#215000
0$
0>
#220000
1$
b1101 :
b1101 0
b10101 5
1>
b11 S
b10 E
b11111010 V
b10 )
0U
#225000
0$
0>
#230000
1$
b10101 :
b1110 0
b10110 5
1>
b100 S
b0 E
b0 F
0D
b11110100 V
0+
b0 *
b0 )
#235000
0$
0>
#240000
1$
b10111 5
1>
b1 S
b110 T
b11 V
1U
#245000
0$
0>
#250000
1$
b11000 5
1>
b10 S
b1 E
b110 F
1D
b11111101 V
1+
b110 *
b1 )
0U
#255000
0$
0>
#260000
1$
b1110 :
b1111 0
b11001 5
1>
b11 S
b0 E
b0 F
0D
b11110111 V
0+
b0 *
b0 )
#265000
0$
0>
#270000
1$
b11010 5
1>
b100 S
b11110001 V
#275000
0$
0>
#280000
1$
b11011 5
1>
b1 S
b111 T
b11 L
b0 V
#285000
0$
0>
b11 K
b0 L
b1 E
b111 F
1D
1+
b111 *
b1 )
#290000
1$
b1111 :
b10000 0
b11100 5
1>
b0 K
b0 M
b0 N
b0 O
b0 S
b0 P
b0 Q
b0 R
b0 T
b1 L
0D
b0 E
b0 F
b0 *
b0 )
0+
#295000
0$
0>
b1 K
#300000
1$
b11101 5
1>
0C
0,
#305000
0$
b11 /
0>
#310000
1$
b11110 5
1>
#315000
0$
1&
1@
0>
#318000
b1 '
b1 (
b1 B
b1 A
#320000
1$
b11111 5
1>
b1 M
b1 P
#322000
bz '
bz (
bz B
bz A
#325000
0$
0&
0@
0>
#328000
b111001 <
b111 '
b1 (
b1 B
b111 A
#330000
1$
b100000 5
1>
b111 N
b1 Q
b1 S
b1 T
1C
b11111010 V
1,
#332000
bz '
bz (
bz B
bz A
#335000
0$
0>
#338000
b1011 =
b1 '
b11 (
b11 B
b1 A
#340000
1$
b100001 5
1>
b1 O
b11 R
b10 L
b1100 V
1U
#342000
bz '
bz (
b110 -
bz B
bz A
#345000
0$
0>
b10 K
#350000
1$
b100010 5
1>
b10 S
b1 E
b1 F
1D
b1010 V
1+
b1 *
b1 )
#355000
0$
0>
#360000
1$
b1001 :
b10001 0
b100011 5
1>
b11 S
b10 E
b1000 V
b10 )
#365000
0$
0>
#370000
1$
b10001 :
b10010 0
b100100 5
1>
b100 S
b11 E
b110 V
b11 )
#375000
0$
0>
#380000
1$
b11001 :
b10011 0
b100101 5
1>
b101 S
b100 E
b100 V
b100 )
#385000
0$
0>
#390000
1$
b100001 :
b10100 0
b100110 5
1>
b110 S
b101 E
b10 V
b101 )
#395000
0$
0>
#400000
1$
b101001 :
b10101 0
b100111 5
1>
b111 S
b110 E
b0 V
b110 )
#405000
0$
0>
#410000
1$
b110001 :
b10110 0
b101000 5
1>
b1 S
b10 T
b111 E
b110 V
b111 )
#415000
0$
0>
#420000
1$
b111001 :
b10111 0
b101001 5
1>
b10 S
b1 E
b10 F
b100 V
b10 *
b1 )
#425000
0$
0>
#430000
1$
b1010 :
b11000 0
b101010 5
1>
b11 S
b10 E
b10 V
b10 )
#435000
0$
0>
#440000
1$
b10010 :
b11001 0
b101011 5
1>
b100 S
b11 E
b0 V
b11 )
#445000
0$
0>
#450000
1$
b11010 :
b11010 0
b101100 5
1>
b101 S
b100 E
b11111110 V
b100 )
0U
#455000
0$
0>
#460000
1$
b100010 :
b11011 0
b101101 5
1>
b110 S
b0 E
b0 F
0D
b11111100 V
0+
b0 *
b0 )
#465000
0$
0>
#470000
1$
b101110 5
1>
b111 S
b11111010 V
#475000
0$
0>
#480000
1$
b101111 5
1>
b1 S
b11 T
b11 L
b0 V
#485000
0$
0>
b11 K
b0 L
b1 E
b11 F
1D
1+
b11 *
b1 )
#490000
1$
b1011 :
b11100 0
b1011011110011000 4
